seg_crf/__init__.py
seg_crf/seg_crf.py
seg_crf-1.0.0.dist-info/LICENSE
seg_crf-1.0.0.dist-info/METADATA
seg_crf-1.0.0.dist-info/WHEEL
seg_crf-1.0.0.dist-info/top_level.txt
seg_crf-1.0.0.dist-info/RECORD
