Metadata-Version: 2.1
Name: seg-crf
Version: 1.0.0
Summary: Conditional Random Field Implementation for segmentation models as used in Deeplab-v2
Home-page: https://github.com/Mr-TalhaIlyas/Conditional-Random-Fields-CRF
Author: Talha Ilyas
Author-email: mr.talhailyas@gmail.com
License: UNKNOWN
Keywords: python,conditional random fields,segmentation,crf,semantic segmentation,fully connected crfdense crf,deeplabv2
Platform: UNKNOWN
Classifier: Intended Audience :: Education
Classifier: Programming Language :: Python :: 3.6
Classifier: License :: OSI Approved :: MIT License
Classifier: Operating System :: OS Independent
Requires-Dist: gray2color
Requires-Dist: pydensecrf
